{"cameraMode":{"drawMode":0,"name":"Shaded","section":"Shading Mode"},"sceneLighting":true,"audioPlay":false,"sceneViewState":{"showFog":true,"showMaterialUpdate":false,"showSkybox":true,"showFlares":true,"showImageEffects":true,"showParticleSystems":true},"in2DMode":false,"pivot":{"x":52.71417236328125,"y":38.54179382324219,"z":91.03620147705078},"rotation":{"x":0.08351089060306549,"y":0.9149529337882996,"z":-0.26668569445610049,"w":0.29203924536705019},"size":1.7320507764816285,"orthographic":false}